flask_restful_auth/__init__.py
flask_restful_auth/__main__.py
flask_restful_auth/decorators.py
Flask_RESTful_Auth-0.0.4.dist-info/LICENSE
Flask_RESTful_Auth-0.0.4.dist-info/METADATA
Flask_RESTful_Auth-0.0.4.dist-info/WHEEL
Flask_RESTful_Auth-0.0.4.dist-info/entry_points.txt
Flask_RESTful_Auth-0.0.4.dist-info/top_level.txt
Flask_RESTful_Auth-0.0.4.dist-info/RECORD
